itaewon
