Metadata-Version: 2.1
Name: itaewon
Version: 0.1.4
Summary: A personal python library to speed up my workflow
Home-page: https://github.com/benjcabalona1029/itaewon
Author: Benjamin Cabalona Jr
Author-email: benjcabalonajr@gmail.com
License: MIT License
Platform: UNKNOWN
